simple_env_config/__init__.py
simple_env_config/converters.py
simple_env_config/env_config.py
simple_env_config/errors.py
simple_env_config-0.2.dist-info/LICENSE
simple_env_config-0.2.dist-info/METADATA
simple_env_config-0.2.dist-info/WHEEL
simple_env_config-0.2.dist-info/top_level.txt
simple_env_config-0.2.dist-info/RECORD
