Metadata-Version: 2.1
Name: simple-env-config
Version: 0.2
Summary: Make use of environment variables for configuration easy
Home-page: https://github.com/freininghaus/simple_env_config
Author: Frank Reininghaus
Author-email: frank78ac@googlemail.com
License: MIT
Keywords: env environment config decorator
Platform: UNKNOWN
Classifier: Programming Language :: Python :: 3
Classifier: License :: OSI Approved :: MIT License
Classifier: Operating System :: OS Independent
Requires-Python: >=3.6
